pytest_sql_bigquery/__init__.py
pytest_sql_bigquery/converter.py
pytest_sql_bigquery/integrations/__init__.py
pytest_sql_bigquery/integrations/pytest.py
pytest_sql_bigquery-0.0.3.dist-info/WHEEL
pytest_sql_bigquery-0.0.3.dist-info/METADATA
pytest_sql_bigquery-0.0.3.dist-info/RECORD
