Metadata-Version: 2.1
Name: pytest-sql-bigquery
Version: 0.0.3
Summary: Yet another SQL-testing framework for BigQuery provided by pytest plugin 
License: MIT
Keywords: sql,bigquery,pytest
Author: TKNGUE
Author-email: takegue@gmail.com
Requires-Python: >=3.7,<4.0
Classifier: License :: OSI Approved :: MIT License
Classifier: Programming Language :: Python :: 3
Classifier: Programming Language :: Python :: 3.7
Classifier: Programming Language :: Python :: 3.8
Requires-Dist: google-cloud-bigquery
Requires-Dist: pytest
Requires-Dist: sqlparse (==0.2.4)
Requires-Dist: tabulate
